dj3base/__init__.py
dj3base/admin/__init__.py
dj3base/admin/ordered_admin_site.py
dj3base/admin/readonly_model_admin.py
dj3base/admin/throttled_login_form.py
dj3base/locale/zh_Hans/LC_MESSAGES/django.mo
dj3base/locale/zh_Hans/LC_MESSAGES/django.po
dj3base/middlewares/__init__.py
dj3base/middlewares/error_handling_middleware.py
dj3base/utils/__init__.py
dj3base/utils/email_utils.py
dj3base/utils/log_utils.py
dj3base/utils/permission_utils.py
dj3base/utils/request_utils.py
dj3base/utils/response_utils.py
dj3base/utils/test_utils.py
dj3base/utils/validator_utils.py
dj3base/views/__init__.py
dj3base/views/post_json_view.py
dj3base-0.3.1.dist-info/LICENSE
dj3base-0.3.1.dist-info/METADATA
dj3base-0.3.1.dist-info/WHEEL
dj3base-0.3.1.dist-info/top_level.txt
dj3base-0.3.1.dist-info/RECORD
