Metadata-Version: 2.1
Name: dj3base
Version: 0.3.1
Summary: dj3base contains some small tools for Django.
Author-email: three-kinds <3179158552@qq.com>
License: MIT
Project-URL: Homepage, https://github.com/three-kinds/dj3base
Project-URL: Source, https://github.com/three-kinds/dj3base
Classifier: Development Status :: 2 - Pre-Alpha
Classifier: Intended Audience :: Developers
Classifier: License :: OSI Approved :: MIT License
Classifier: Operating System :: OS Independent
Classifier: Programming Language :: Python
Classifier: Programming Language :: Python :: 3
Classifier: Programming Language :: Python :: 3 :: Only
Classifier: Programming Language :: Python :: 3.10
Classifier: Programming Language :: Python :: 3.11
Classifier: Programming Language :: Python :: 3.12
Classifier: Programming Language :: Python :: 3.13
Classifier: Topic :: Software Development :: Libraries :: Python Modules
Classifier: Framework :: Django
Requires-Python: >=3.10
License-File: LICENSE
Requires-Dist: django
Requires-Dist: a3exception>=0.3.0
Requires-Dist: a3json-struct>=0.3.0
